ros_cdk_dashvector/__init__.py
ros_cdk_dashvector/py.typed
ros_cdk_dashvector/_jsii/__init__.py
ros_cdk_dashvector/_jsii/ros-cdk-dashvector@1.11.0.jsii.tgz
ros_cdk_dashvector-1.11.0.dist-info/LICENSE
ros_cdk_dashvector-1.11.0.dist-info/METADATA
ros_cdk_dashvector-1.11.0.dist-info/NOTICE
ros_cdk_dashvector-1.11.0.dist-info/WHEEL
ros_cdk_dashvector-1.11.0.dist-info/top_level.txt
ros_cdk_dashvector-1.11.0.dist-info/RECORD
