Metadata-Version: 2.1
Name: ros-cdk-dashvector
Version: 1.11.0
Summary: Aliyun SDK Copyright (C) Alibaba Cloud Computing All rights reserved. http://www.aliyun.com
Home-page: https://github.com/aliyun/Resource-Orchestration-Service-Cloud-Development-Kit.git
Author: ROS Development Team
License: Apache-2.0
Project-URL: Source, https://github.com/aliyun/Resource-Orchestration-Service-Cloud-Development-Kit.git
Classifier: Intended Audience :: Developers
Classifier: Operating System :: OS Independent
Classifier: Programming Language :: JavaScript
Classifier: Programming Language :: Python :: 3 :: Only
Classifier: Programming Language :: Python :: 3.7
Classifier: Programming Language :: Python :: 3.8
Classifier: Programming Language :: Python :: 3.9
Classifier: Programming Language :: Python :: 3.10
Classifier: Programming Language :: Python :: 3.11
Classifier: Typing :: Typed
Classifier: License :: OSI Approved
Classifier: Programming Language :: Python :: 3
Requires-Python: ~=3.7
License-File: LICENSE
License-File: NOTICE
Requires-Dist: constructs (<4.0.0,>=3.0.4)
Requires-Dist: jsii (<=1.85.0,>1.12.0)
Requires-Dist: publication (>=0.0.3)
Requires-Dist: ros-cdk-core (<2.0.0,>=1.7.0)
Requires-Dist: typeguard (~=2.13.3)
